benchmarks/__init__.py
benchmarks/benchmark_correct.py
benchmarks/benchmark_fit.py
benchmarks/benchmark_plot.py
detectorcal/__init__.py
detectorcal/correct.py
detectorcal/fit.py
detectorcal/plot.py
detectorcal-0.0.1.dist-info/LICENSE
detectorcal-0.0.1.dist-info/METADATA
detectorcal-0.0.1.dist-info/WHEEL
detectorcal-0.0.1.dist-info/top_level.txt
detectorcal-0.0.1.dist-info/RECORD
