Metadata-Version: 2.1
Name: detectorcal
Version: 0.0.1
Summary: Ring artefact suppression in X-ray CT using pixel-wise linear correction
Home-page: https://gitlab.erc.monash.edu.au/xrayimaging/detector-calibration
Author: Abigail McGovern
Author-email: Abigail.McGovern1@monash.edu
License: BSD 2-Clause License
Project-URL: Bug Tracker, https://gitlab.erc.monash.edu.au/xrayimaging/detector-calibration/-/issues
Platform: UNKNOWN
Classifier: Programming Language :: Python :: 3
Classifier: License :: OSI Approved :: BSD License
Classifier: Operating System :: OS Independent
Classifier: Intended Audience :: Science/Research
Classifier: Topic :: Scientific/Engineering
Classifier: Topic :: Scientific/Engineering :: Image Processing
Classifier: Topic :: Scientific/Engineering :: Physics
Requires-Python: >=3.6
License-File: LICENSE
Requires-Dist: dask
Requires-Dist: distributed
Requires-Dist: scipy
Requires-Dist: numpy
Requires-Dist: matplotlib
Requires-Dist: scikit-image
Requires-Dist: pytest
Requires-Dist: sphinx
Requires-Dist: h5py
Requires-Dist: zarr
Requires-Dist: numba
Requires-Dist: numpydoc
Provides-Extra: gpu
Requires-Dist: cupy ; extra == 'gpu'
Provides-Extra: testing
Requires-Dist: pytest ; extra == 'testing'
Requires-Dist: pytest-cov ; extra == 'testing'
Requires-Dist: coverage ; extra == 'testing'
Requires-Dist: asv ; extra == 'testing'
